Lab3/mealy.v
module mealy (clk, rst, inp, outp);
	input clk, rst, inp;
	output outp;
	reg [1:0] state;
	reg outp;
	always @( posedge clk, posedge rst ) begin
		if( rst ) begin
		state <= 2'b00;
		outp <= 0;
		end
		
		else begin
			case( state )
			2'b00: begin
				if( inp ) begin
				state <= 2'b01;
				outp <= 0;
				end
				else begin
				state <= 2'b10;
				outp <= 0;
				end
			end
			2'b01: begin
				if( inp ) begin
				state <= 2'b00;
				outp <= 1;
				end
				else begin
				state <= 2'b10;
				outp <= 0;
				end
			end
			2'b10: begin
				if( inp ) begin
				state <= 2'b01;
				outp <= 0;
				end
				else begin
				state <= 2'b00;
				outp <= 1;
				end
			end

		default: begin
		state <= 2'b00;
		outp <= 0;
		end
			endcase
	end
	end
endmodule
	
	
// testbench
// Test Bench
module mealy_test;
reg clk, rst, inp;
wire outp;
reg[15:0] sequence;
integer i;
mealy duty( clk, rst, inp, outp);
initial
begin
		  $dumpfile("mealy_test.vcd");
		  $dumpvars(0,mealy_test);
clk = 0;
rst = 1;
sequence = 16'b0101_0111_0111_0010;
#5 rst = 0;
for( i = 0; i <= 15; i = i + 1)
begin
inp = sequence[i];
#2 clk = 1;
#2 clk = 0;
$display("State = ", duty.state, " Input = ", inp, ", Output = ",
outp);
end
testing;
end
task testing;
for( i = 0; i <= 15; i = i + 1)
begin
inp = $random % 2;
#2 clk = 1;
#2 clk = 0;
$display("State = ", duty.state, " Input = ", inp, "Output =", outp);
end
endtask
endmodule

Lab3/gktoutputfile.vcd
$date
	Thu Sep 26 15:43:56 2019
$end
$version
	GTKWave Analyzer v3.3.66 (w)1999-2015 BSI
$end
$timescale
	1 s
$end
$scope module mealy_test $end
$var wire 32 # i $end
$var wire 1 & rst $end
$var wire 1 " clk $end
$var wire 16 ' sequence[15:0] $end
$var wire 1 $ inp $end
$var wire 1 % outp $end
$upscope $end
$enddefinitions $end
$dumpvars
#0
0%
b101011101110010 '
bx #
1&
0"
x$
#5
0$
b0 #
0&
#7
1"
#9
0"
1$
b1 #
#11
1"
#13
0"
b10 #
0$
#15
1"
#17
0"
b11 #
#19
1%
1"
#21
0"
b100 #
1$
#23
1"
0%
#25
b101 #
0"
#27
1"
1%
#29
0"
b110 #
#31
0%
1"
#33
0"
b111 #
0$
#35
1"
#37
0"
1$
b1000 #
#39
1"
#41
0"
b1001 #
#43
1"
1%
#45
b1010 #
0"
#47
1"
0%
#49
0"
0$
b1011 #
#51
1"
#53
0"
b1100 #
1$
#55
1"
#57
0"
0$
b1101 #
#59
1"
#61
0"
b1110 #
1$
#63
1"
#65
0"
0$
b1111 #
#67
1"
#69
0"
b0 #
#71
1"
1%
#73
0"
b1 #
1$
#75
1"
0%
#77
0"
b10 #
#79
1%
1"
#81
0"
b11 #
#83
1"
0%
#85
b100 #
0"
#87
1"
1%
#89
0"
b101 #
#91
0%
1"
#93
0"
b110 #
#95
1"
1%
#97
b111 #
0$
0"
#99
1"
0%
#101
0"
b1000 #
1$
#103
1"
#105
0"
b1001 #
#107
1%
1"
#109
0"
b1010 #
0$
#111
1"
0%
#113
1$
b1011 #
0"
#115
1"
#117
0"
b1100 #
#119
1%
1"
#121
0"
b1101 #
0$
#123
1"
0%
#125
1$
b1110 #
0"
#127
1"
#129
0"
0$
b1111 #
#131
1"
#133
0"
b10000 #
